inventree_kom2/KiCadClasses.py
inventree_kom2/Kom2Plugin.py
inventree_kom2/__init__.py
inventree_kom2/templates/inventree_kom2/index.html
inventree_kom2/templates/inventree_kom2/script.js
inventree_kom2-1.1.dist-info/METADATA
inventree_kom2-1.1.dist-info/WHEEL
inventree_kom2-1.1.dist-info/entry_points.txt
inventree_kom2-1.1.dist-info/top_level.txt
inventree_kom2-1.1.dist-info/RECORD
