Metadata-Version: 2.1
Name: inventree-kom2
Version: 1.1
Summary: Use InvenTree with KiCad
Author-email: Matthias Mair <code@mjmair.com>
License: MIT license
Project-URL: Repository, https://github.com/matmair/inventree-kom2
Project-URL: Bug Tracker, https://github.com/matmair/inventree-kom2/issues
Keywords: inventree,inventree-plugin,inventree-kom2
Classifier: Programming Language :: Python :: 3
Classifier: Operating System :: OS Independent
Classifier: Development Status :: 5 - Production/Stable
Classifier: Environment :: Plugins
Classifier: Framework :: Django
Classifier: Intended Audience :: Developers
Classifier: Intended Audience :: Manufacturing
Classifier: Intended Audience :: End Users/Desktop
Classifier: Topic :: Scientific/Engineering
Classifier: License :: OSI Approved :: MIT License
Requires-Python: >=3.9
Requires-Dist: django
Provides-Extra: dev
Requires-Dist: twine ; extra == 'dev'
Requires-Dist: setuptools ; extra == 'dev'
